jara_utils/__init__.py
jara_utils/cli_output.py
jara_utils/constants.py
jara_utils/decorators.py
jara_utils/dotenv_configs.py
jara_utils/environment.py
jara_utils/exceptions.py
jara_utils/normalization/__init__.py
jara_utils/normalization/boolean.py
jara_utils/normalization/datetime.py
jara_utils/normalization/integer.py
jara_utils/normalization/iterable.py
jara_utils/normalization/string.py
jara_utils-1.2.1.dist-info/METADATA
jara_utils-1.2.1.dist-info/WHEEL
jara_utils-1.2.1.dist-info/RECORD
