Metadata-Version: 2.1
Name: jara-utils
Version: 1.2.1
Summary: A package with basic stuff.
Home-page: https://github.com/senciucserban/jara-utils
Author: Serban Senciuc
Author-email: senciuc.serban@gmail.com
Requires-Python: >=3.11,<4.0
Classifier: Programming Language :: Python :: 3
Classifier: Programming Language :: Python :: 3.11
Classifier: Programming Language :: Python :: 3.12
Classifier: Topic :: Utilities
Provides-Extra: all
Provides-Extra: dotenv
Requires-Dist: python-dotenv (>=1.0.0,<2.0.0) ; extra == "dotenv" or extra == "all"
Requires-Dist: pytz (>=2024.1,<2025.0)
Requires-Dist: types-pytz (>=2024.1.0.20240203,<2025.0.0.0)
Project-URL: Repository, https://github.com/senciucserban/jara-utils
